nexus_vpn/__init__.py
nexus_vpn/cli.py
nexus_vpn/core/__init__.py
nexus_vpn/core/cert_mgr.py
nexus_vpn/core/installer.py
nexus_vpn/core/system.py
nexus_vpn/core/user_mgr.py
nexus_vpn/protocols/__init__.py
nexus_vpn/protocols/ikev2.py
nexus_vpn/protocols/v2ray.py
nexus_vpn/utils/__init__.py
nexus_vpn/utils/logger.py
nexus_vpn/utils/sudo.py
nexus_vpn-0.1.6.dist-info/licenses/LICENSE
nexus_vpn-0.1.6.dist-info/METADATA
nexus_vpn-0.1.6.dist-info/WHEEL
nexus_vpn-0.1.6.dist-info/entry_points.txt
nexus_vpn-0.1.6.dist-info/top_level.txt
nexus_vpn-0.1.6.dist-info/RECORD
