Metadata-Version: 2.4
Name: nexus-vpn
Version: 0.1.6
Summary: 一键部署 VLESS-Reality + IKEv2 VPN 的综合代理工具
Home-page: https://github.com/alphajc/nexus-vpn
Author: Jerry
Author-email: Jerry <jerry@example.com>
License-Expression: MIT
Project-URL: Homepage, https://github.com/alphajc/nexus-vpn
Project-URL: Repository, https://github.com/alphajc/nexus-vpn
Project-URL: Issues, https://github.com/alphajc/nexus-vpn/issues
Keywords: vpn,proxy,vless,reality,ikev2,xray,strongswan
Classifier: Development Status :: 4 - Beta
Classifier: Environment :: Console
Classifier: Intended Audience :: System Administrators
Classifier: Operating System :: POSIX :: Linux
Classifier: Programming Language :: Python :: 3
Classifier: Programming Language :: Python :: 3.8
Classifier: Programming Language :: Python :: 3.9
Classifier: Programming Language :: Python :: 3.10
Classifier: Programming Language :: Python :: 3.11
Classifier: Programming Language :: Python :: 3.12
Classifier: Topic :: Internet :: Proxy Servers
Classifier: Topic :: System :: Networking
Requires-Python: >=3.8
License-File: LICENSE
Requires-Dist: click>=8.1.0
Requires-Dist: rich>=13.0.0
Requires-Dist: qrcode>=7.4.0
Requires-Dist: jinja2>=3.1.0
Provides-Extra: dev
Requires-Dist: pytest>=7.0.0; extra == "dev"
Requires-Dist: pytest-cov>=4.0.0; extra == "dev"
Requires-Dist: pytest-mock>=3.10.0; extra == "dev"
Dynamic: author
Dynamic: home-page
Dynamic: license-file
Dynamic: requires-python
